mfd_common_libs/__init__.py
mfd_common_libs/custom_logger.py
mfd_common_libs/disable_logger.py
mfd_common_libs/exceptions.py
mfd_common_libs/log_func_info.py
mfd_common_libs/log_levels.py
mfd_common_libs/os_supported_decorator.py
mfd_common_libs/timeout_counter.py
mfd_common_libs-1.11.0.dist-info/licenses/AUTHORS.md
mfd_common_libs-1.11.0.dist-info/licenses/LICENSE.md
mfd_common_libs-1.11.0.dist-info/METADATA
mfd_common_libs-1.11.0.dist-info/WHEEL
mfd_common_libs-1.11.0.dist-info/top_level.txt
mfd_common_libs-1.11.0.dist-info/RECORD
