Metadata-Version: 2.4
Name: mfd-common-libs
Version: 1.11.0
Summary: Module with common libraries and methods used in Modular Framework Design (MFD) ...
Project-URL: Homepage, https://github.com/intel/mfd
Project-URL: Repository, https://github.com/intel/mfd-common-libs
Project-URL: Issues, https://github.com/intel/mfd-common-libs/issues
Project-URL: Changelog, https://github.com/intel/mfd-common-libs/blob/main/CHANGELOG.md
Requires-Python: <3.14,>=3.10
License-File: LICENSE.md
License-File: AUTHORS.md
Dynamic: license-file
